toonstream/__init__.py
toonstream/cli.py
toonstream/decoder.py
toonstream/encoder.py
toonstream/exceptions.py
toonstream/pickle_utils.py
toonstream/tensor_utils.py
toonstream/tron_decoder.py
toonstream/tron_encoder.py
toonstream/unified_api.py
toonstream-2.0.0.dist-info/licenses/LICENSE
toonstream-2.0.0.dist-info/METADATA
toonstream-2.0.0.dist-info/WHEEL
toonstream-2.0.0.dist-info/top_level.txt
toonstream-2.0.0.dist-info/RECORD
