Metadata-Version: 2.4
Name: toonstream
Version: 2.0.0
Summary: Token Oriented Object Notation - Efficient data serialization for LLMs with TOON and TRON formats
Home-page: https://github.com/vivekpandian08/toonstream
Author: Vivek Pandian
Author-email: Vivek Pandian <vivekpandian08@gmail.com>
Maintainer-email: Vivek Pandian <vivekpandian08@gmail.com>
License-Expression: MIT
Project-URL: Homepage, https://github.com/vivekpandian08/toonstream
Project-URL: Documentation, https://github.com/vivekpandian08/toonstream#readme
Project-URL: Repository, https://github.com/vivekpandian08/toonstream
Project-URL: Bug Tracker, https://github.com/vivekpandian08/toonstream/issues
Project-URL: Changelog, https://github.com/vivekpandian08/toonstream/releases
Keywords: toon,tron,json,serialization,tokens,llm,optimization,csv,tabular,gpt
Classifier: Development Status :: 5 - Production/Stable
Classifier: Intended Audience :: Developers
Classifier: Topic :: Software Development :: Libraries :: Python Modules
Classifier: Topic :: Text Processing :: Markup
Classifier: Topic :: Scientific/Engineering :: Artificial Intelligence
Classifier: Operating System :: OS Independent
Classifier: Programming Language :: Python :: 3
Classifier: Programming Language :: Python :: 3.8
Classifier: Programming Language :: Python :: 3.9
Classifier: Programming Language :: Python :: 3.10
Classifier: Programming Language :: Python :: 3.11
Classifier: Programming Language :: Python :: 3.12
Classifier: Programming Language :: Python :: 3.13
Classifier: Programming Language :: Python :: 3 :: Only
Classifier: Typing :: Typed
Requires-Python: >=3.8
License-File: LICENSE
Provides-Extra: dev
Requires-Dist: pytest>=7.0.0; extra == "dev"
Requires-Dist: pytest-cov>=4.0.0; extra == "dev"
Requires-Dist: black>=23.0.0; extra == "dev"
Requires-Dist: ruff>=0.1.0; extra == "dev"
Provides-Extra: test
Requires-Dist: pytest>=7.0.0; extra == "test"
Requires-Dist: pytest-cov>=4.0.0; extra == "test"
Requires-Dist: tiktoken>=0.5.0; extra == "test"
Provides-Extra: benchmark
Requires-Dist: tiktoken>=0.5.0; extra == "benchmark"
Provides-Extra: torch
Requires-Dist: torch>=2.0.0; extra == "torch"
Provides-Extra: all
Requires-Dist: pytest>=7.0.0; extra == "all"
Requires-Dist: pytest-cov>=4.0.0; extra == "all"
Requires-Dist: tiktoken>=0.5.0; extra == "all"
Requires-Dist: torch>=2.0.0; extra == "all"
Dynamic: author
Dynamic: home-page
Dynamic: license-file
Dynamic: requires-python
